{
  "slider-wrapper": "_474ctx2d",
  "slider": "_4ju5m3f9",
  "slick-slider": "_4s85sv58",
  "slick-list": "_87w2sppt",
  "dragging": "_7ct9s12f",
  "slick-track": "_6ff6bh4p",
  "slick-loading": "_6egy7369",
  "slick-slide": "_4kjjaktn",
  "slick-initialized": "_4c8jasdu",
  "slick-vertical": "_2zfh5s2x",
  "slick-arrow": "_6xs141qh",
  "slick-hidden": "_6j594xr2",
  "slick-next": "_654spc7g",
  "slick-prev": "_w99kkbfy",
  "slick-disabled": "_5gfauzfp",
  "slick-dotted": "_ndc8p5td",
  "slick-dots": "_4autn6nq",
  "slick-active": "_dx494e33",
  "site-header": "_6k1jzjhu",
  "header__bg": "_6r95umg1",
  "logo": "_5jpxtyxv",
  "main_nav": "_61pcfpd8",
  "nav-item-link__active": "_48b4v3u6",
  "single-nav": "_5vh5g7zp",
  "nav-toggle": "_6ahdp7wm",
  "burger": "_5unvmwy6",
  "category-page": "_3myxe2sh",
  "front-page": "_85py5cy9",
  "for-h": "_65vfbjmf",
  "main-text": "_65epb9b9",
  "front__reg-block": "_78xykszu",
  "front__reg-button": "_6d2scg7w",
  "front__text-wrapper": "_4atd8fm9",
  "prise": "_2qr6y5jh",
  "prise__text": "_5h1enk5f",
  "prise__percent": "_5mbstuef",
  "prise__link": "_8cfcacwx",
  "prise__button": "_yxg9u5aq",
  "page": "_489n1gxt",
  "item-404": "_47bxkuuf",
  "err-text": "_madpbkuw",
  "footer__bages": "_3376x6ga",
  "footer__bages-wrapper": "_8je3vkfm",
  "footer__bage_item": "_7a6q5jc9",
  "footer__logo": "_6kqprwk3",
  "clearfix": "_6yyeqwb1",
  "kill-list": "_2hey1wmm",
  "alignnone": "_4r4gugzy",
  "aligncenter": "_4pqhhgm5",
  "alignright": "_2txeggma",
  "alignleft": "_7wjmugjv",
  "center-block": "_4nurjgjp",
  "container": "_3pee52d5",
  "game-picture-wrapper": "_7m7ngae3"
}